edaac/__init__.py
edaac/enum.py
edaac/log.py
edaac/version.py
edaac/metrics/__init__.py
edaac/metrics/parsers/__init__.py
edaac/metrics/parsers/innovus_area_report.py
edaac/metrics/parsers/innovus_conn_report.py
edaac/metrics/parsers/innovus_drc_report.py
edaac/metrics/parsers/innovus_log.py
edaac/metrics/parsers/innovus_power_report.py
edaac/metrics/parsers/innovus_timing_report.py
edaac/metrics/parsers/openroad_log.py
edaac/metrics/parsers/yosys_log.py
edaac/models/__init__.py
edaac/models/design.py
edaac/models/flow.py
edaac/models/project.py
edaac/models/stage.py
edaac/models/technology.py
edaac/models/tool.py
test/__init__.py
test/test_add_flow.py
test/test_initialize_project.py
test/test_innovus_area.py
test/test_innovus_conn.py
test/test_innovus_drc.py
test/test_innovus_log.py
test/test_innovus_power.py
test/test_innovus_timing.py
test/test_openroad_log.py
test/test_yosys_log.py
edaac-0.0.21.dist-info/AUTHORS
edaac-0.0.21.dist-info/LICENSE
edaac-0.0.21.dist-info/METADATA
edaac-0.0.21.dist-info/WHEEL
edaac-0.0.21.dist-info/top_level.txt
edaac-0.0.21.dist-info/RECORD
