Metadata-Version: 2.1
Name: edaac
Version: 0.0.21
Summary: Your day-to-day EDA analytics tool
Home-page: https://github.com/abdelrahmanhosny/EDAAC
Author: Abdelrahman Hosny
Author-email: abdelrahman_hosny@brown.edu
License: BSD-3 License
Download-URL: https://github.com/abdelrahman/EDAAC/archive/v_0.0.21.tar.gz
Keywords: EDA,Electronic,Design,Automation,Data,Analytics
Platform: UNKNOWN
Classifier: Development Status :: 3 - Alpha
Classifier: Intended Audience :: Developers
Classifier: Topic :: Scientific/Engineering :: Electronic Design Automation (EDA)
Classifier: License :: OSI Approved :: BSD License
Classifier: Programming Language :: Python :: 3
Classifier: Programming Language :: Python :: 3.4
Classifier: Programming Language :: Python :: 3.5
Classifier: Programming Language :: Python :: 3.6
Requires-Dist: mongoengine (==0.19.1)
Requires-Dist: pymongo (==3.10.1)
Requires-Dist: six (==1.14.0)
